pydeal_line_length/__init__.py
pydeal_line_length/checker.py
pydeal_line_length-0.1.0.dist-info/LICENSE
pydeal_line_length-0.1.0.dist-info/WHEEL
pydeal_line_length-0.1.0.dist-info/METADATA
pydeal_line_length-0.1.0.dist-info/RECORD
